tests/__init__.py
tests/test_api_interface.py
tests/test_base.py
tests/test_subclasses.py
unsplashapi/__init__.py
unsplashapi/api.py
unsplashapi/base.py
unsplashapi/collection.py
unsplashapi/photos.py
unsplashapi/topics_stats.py
unsplashapi/user.py
unsplashapi-0.0.5.dist-info/LICENSE
unsplashapi-0.0.5.dist-info/METADATA
unsplashapi-0.0.5.dist-info/WHEEL
unsplashapi-0.0.5.dist-info/top_level.txt
unsplashapi-0.0.5.dist-info/RECORD
