Metadata-Version: 2.1
Name: unsplashapi
Version: 0.0.5
Summary: Inofficial API Wrapper for Unsplash API
Author: SimonStaehli
Author-email: <simon.staehli@students.fhnw.ch>
License: UNKNOWN
Keywords: python,api,unsplash api,unsplash,unsplashapi
Platform: UNKNOWN
Classifier: Development Status :: 1 - Planning
Classifier: Intended Audience :: Developers
Classifier: Programming Language :: Python :: 3
Classifier: Operating System :: Unix
Classifier: Operating System :: MacOS :: MacOS X
Classifier: Operating System :: Microsoft :: Windows
Requires-Python: >=3
License-File: LICENSE
Requires-Dist: requests
